convo_lang/__init__.py
convo_lang/conversation.py
convo_lang/convo_cli_path.py
convo_lang/convo_cli_runner.py
convo_lang/error_utils.py
convo_lang/errors.py
convo_lang/mock_runner.py
convo_lang/utils/__init__.py
convo_lang-0.6.2.dist-info/METADATA
convo_lang-0.6.2.dist-info/WHEEL
convo_lang-0.6.2.dist-info/licenses/LICENSE
convo_lang-0.6.2.dist-info/RECORD
