Metadata-Version: 2.4
Name: convo_lang
Version: 0.6.2
Summary: A conversational prompting and programming language
Project-URL: Repository, https://github.com/convo-lang/convo-lang/blob/main/packages/convo-lang-py
Author-email: Scott Vance <scott@iyio.io>
Maintainer-email: Sergey Inozemtsev <inozemtsevserge@gmail.com>
License:                     GNU AFFERO GENERAL PUBLIC LICENSE
License-File: LICENSE
Keywords: ai,convo-lang,open-ai,prompt,prompt-engineering
Classifier: License :: OSI Approved :: MIT License
Classifier: Operating System :: OS Independent
Classifier: Programming Language :: Python :: 3
Requires-Python: >=3.8
